design.sv
//Fault Detection FSM
//Assuming Persistence if fault exists more than 10 clk cycles
//Transient spike if fault less than 10 clk cycles
module fault_detect(
  input logic clk, rst,
  input logic [3:0]cell_volts,//Assuming normal volt required is 12V
  input logic [3:0]current,//Assuming ideal required current is 10A
  input logic [5:0]temp, //Assuming safe temperature of battery is 30 degree C

  
  output logic minor_fault, major_fault, //minor fault for transient spike and major fault for fault which require immediate assistance
  output logic[1:0] state
  
);
    localparam Persistence=4'd10;
    parameter [1:0]Normal=2'b00,Warning=2'b01, Fault=2'b10,Shutdown=2'b11;
    logic [3:0] cnt;      // persistence counter
    logic       cur_fault;
    logic volt_fault, curr_fault, temp_fault;

	// Fault detection
    assign volt_fault = (cell_volts != 4'd12); // Medium priority = voltage     
    assign curr_fault = (current   != 4'd10); // Lowest priority = current   
    assign temp_fault = (temp > 6'd30); // Highest priority = temperature   

    assign cur_fault = temp_fault | volt_fault | curr_fault;

    logic [1:0] fault_prio;
    always_comb begin
      if (temp_fault)       fault_prio = 2'd3; // highest
      else if (volt_fault)  fault_prio = 2'd2;
      else if (curr_fault)  fault_prio = 2'd1;
      else                  fault_prio = 2'd0;
    end

        
  always_ff @(posedge clk or posedge rst) begin
    if (rst)
      cnt <= 0;
    else if (cur_fault) begin
      if (cnt < Persistence)
        cnt <= cnt + 1;
    end else begin
      cnt <= 0;
    end
  end
//To find the type of fault  
  assign minor_fault = (cur_fault && cnt < Persistence);
  assign major_fault = (cnt >= Persistence);

  
  always_ff @(posedge clk or posedge rst) begin
    if(rst)
      state<=Normal;
    else begin
      case (state)
        Normal: begin
          if (fault_prio == 2'd3) state <= Fault; //if fault is of highest priority 
          else if (major_fault)   state <= Fault; // if the fault persist  
          else if (minor_fault)   state <= Warning;
        end
        Warning: begin
          if (fault_prio == 2'd3) state <= Fault; 
          else if (major_fault) state <= Fault;
          else if (!cur_fault) state <= Normal;
        end
        Fault: begin
          if (fault_prio == 2'd3) state <= Shutdown;
          else if (major_fault) state <= Shutdown;  // if the fault persist
          else if (!cur_fault) state <= Normal;
        end
        Shutdown: state <= Shutdown; // latch until reset
        	
      endcase
    end 
        
  end
endmodule

testbench.sv
//Testbench for Fault detection FSM
//`timescale 1ns/1ps
module tb_fsm;
  logic clk,rst;
  logic[3:0] cell_volts,current;
  logic[5:0]temp;
  logic minor_fault,major_fault;
  logic [1:0] state;
  fault_detect dut(
    .clk(clk),.rst(rst),
    .cell_volts(cell_volts),
    .current(current),
    .temp(temp),
    .minor_fault(minor_fault),
    .major_fault(major_fault),
    .state(state)
  );
  localparam Persistence=4'd10;
  initial clk = 0;
    always #5 clk = ~clk; 
  initial begin
     $dumpfile("tb_fault_fsm.vcd");
     $dumpvars();
  end

  initial begin
    
    rst=1'b1;
    cell_volts=4'd12;
    current=4'd10;
    temp=6'd25;
    #20 rst=1'b0;
    $display("[%0t] Starting FSM operation ", $time);
	#20 cell_volts=4'd8; //Injecting a fault
    repeat(2) #20;
    cell_volts=4'd12;//restoring to normal volt
    #20 cell_volts=4'd15;//Injecting overvolt
    repeat(5) #20;
    cell_volts=4'd12;//restoring to normal volt
    #20 current=4'd7;//low current
    #20
    current=4'd10;//normal current
    #30
    temp=6'd45;// a high temperature 
    repeat(5) #20;
    #40 $finish;
  end
  
  
  always @(posedge clk) begin
    string state_name;
    case(state)
      2'b00: state_name = "Normal";
      2'b01: state_name = "Warning";
      2'b10: state_name = "Fault";
      2'b11: state_name = "Shutdown";
      default: state_name = "Unknown";
    endcase
    $display("%0t : state=%0s minor_fault=%b major_fault=%b",$time, state_name, minor_fault, major_fault);
      end
endmodule

tb_fault_fsm.vcd
$date
    Sep 22, 2025  04:38:47
$end
$version
    TOOL:	xmsim	23.09-s001
$end
$timescale
    1 ns
$end

$scope module tb_fsm $end
$var reg       1 !    clk $end
$var reg       1 "    rst $end
$var reg       4 #    cell_volts [3:0] $end
$var reg       4 $    current [3:0] $end
$var reg       6 %    temp [5:0] $end
$var reg       1 &    minor_fault $end
$var reg       1 '    major_fault $end
$var reg       2 (    state [1:0] $end
$var parameter  4 )    Persistence $end

$scope module dut $end
$var wire      1 *    clk  $end
$var wire      1 +    rst  $end
$var wire      4 ,    cell_volts [3:0] $end
$var wire      4 -    current [3:0] $end
$var wire      6 .    temp [5:0] $end
$var reg       1 /    minor_fault $end
$var reg       1 0    major_fault $end
$var reg       2 1    state [1:0] $end
$var parameter  4 2    Persistence $end
$var parameter  2 3    Normal [1:0] $end
$var parameter  2 4    Warning [1:0] $end
$var parameter  2 5    Fault [1:0] $end
$var parameter  2 6    Shutdown [1:0] $end
$var reg       4 7    cnt [3:0] $end
$var reg       1 8    cur_fault $end
$var reg       1 9    volt_fault $end
$var reg       1 :    curr_fault $end
$var reg       1 ;    temp_fault $end
$var reg       2 <    fault_prio [1:0] $end
$upscope $end

$upscope $end

$enddefinitions $end
$dumpvars
b11 6
b10 5
b1 4
b0 3
b1010 2
b1010 )
0!
1"
b1100 #
b1010 $
b11001 %
0&
0'
b0 (
0*
1+
b1100 ,
b1010 -
b11001 .
0/
00
b0 1
b0 7
08
09
0:
0;
b0 <
$end
#5
1!
1*
#10
0!
0*
#15
1!
1*
#20
0"
0!
0*
0+
#25
1!
1*
#30
0!
0*
#35
1!
1*
#40
b1000 #
0!
0*
b1000 ,
19
18
b10 <
1/
1&
#45
1!
1*
b1 1
b1 7
b1 (
#50
0!
0*
#55
1!
1*
b10 7
#60
0!
0*
#65
1!
1*
b11 7
#70
0!
0*
#75
1!
1*
b100 7
#80
b1100 #
0!
0*
b1100 ,
09
08
b0 <
0/
0&
#85
1!
1*
b0 1
b0 7
b0 (
#90
0!
0*
#95
1!
1*
#100
b1111 #
0!
0*
b1111 ,
19
18
b10 <
1/
1&
#105
1!
1*
b1 1
b1 7
b1 (
#110
0!
0*
#115
1!
1*
b10 7
#120
0!
0*
#125
1!
1*
b11 7
#130
0!
0*
#135
1!
1*
b100 7
#140
0!
0*
#145
1!
1*
b101 7
#150
0!
0*
#155
1!
1*
b110 7
#160
0!
0*
#165
1!
1*
b111 7
#170
0!
0*
#175
1!
1*
b1000 7
#180
0!
0*
#185
1!
1*
b1001 7
#190
0!
0*
#195
1!
1*
b1010 7
0/
10
1'
0&
#200
b1100 #
0!
0*
b1100 ,
09
08
b0 <
#205
1!
1*
b10 1
b0 7
00
0'
b10 (
#210
0!
0*
#215
1!
1*
b0 1
b0 (
#220
b111 $
0!
0*
b111 -
1:
18
b1 <
1/
1&
#225
1!
1*
b1 1
b1 7
b1 (
#230
0!
0*
#235
1!
1*
b10 7
#240
b1010 $
0!
0*
b1010 -
0:
08
b0 <
0/
0&
#245
1!
1*
b0 1
b0 7
b0 (
#250
0!
0*
#255
1!
1*
#260
0!
0*
#265
1!
1*
#270
b101101 %
0!
0*
b101101 .
1;
18
b11 <
1/
1&
#275
1!
1*
b10 1
b1 7
b10 (
#280
0!
0*
#285
1!
1*
b11 1
b10 7
b11 (
#290
0!
0*
#295
1!
1*
b11 7
#300
0!
0*
#305
1!
1*
b100 7
#310
0!
0*
#315
1!
1*
b101 7
#320
0!
0*
#325
1!
1*
b110 7
#330
0!
0*
#335
1!
1*
b111 7
#340
0!
0*
#345
1!
1*
b1000 7
#350
0!
0*
#355
1!
1*
b1001 7
#360
0!
0*
#365
1!
1*
b1010 7
0/
10
1'
0&
